iar_wiki_parser/__init__.py
iar_wiki_parser/wikipedia_parser.py
iar_wiki_parser/wikipedia_parser_consts.py
iar_wiki_parser-1.0.7.dist-info/METADATA
iar_wiki_parser-1.0.7.dist-info/WHEEL
iar_wiki_parser-1.0.7.dist-info/top_level.txt
iar_wiki_parser-1.0.7.dist-info/RECORD
