Metadata-Version: 2.1
Name: iar-wiki-parser
Version: 1.0.7
Summary: A parser for the Spanish Wikipedia.
Home-page: https://pypi.org/project/iar-wiki-parser/
Author: Iván Arias Rodríguez
Author-email: ivan.arias.rodriguez@gmail.com
License: Creative Commons Attribution-NonCommercial-ShareAlike 4.0 International License
Platform: UNKNOWN
Classifier: Programming Language :: Python
Classifier: Development Status :: 1 - Planning
Classifier: Intended Audience :: Science/Research
Classifier: License :: Other/Proprietary License
Classifier: Natural Language :: Spanish
Classifier: Operating System :: OS Independent
Classifier: Programming Language :: Python :: 3 :: Only
Classifier: Topic :: Scientific/Engineering
Requires-Dist: iar-tokenizer
Requires-Dist: urllib3
Requires-Dist: bz2file
